MANIFEST.in
README.md
setup.py
netos_fabric/__init__.py
netos_fabric/filtersets.py
netos_fabric/forms.py
netos_fabric/models.py
netos_fabric/navigation.py
netos_fabric/tables.py
netos_fabric/urls.py
netos_fabric/views.py
netos_fabric.egg-info/PKG-INFO
netos_fabric.egg-info/SOURCES.txt
netos_fabric.egg-info/dependency_links.txt
netos_fabric.egg-info/not-zip-safe
netos_fabric.egg-info/top_level.txt
netos_fabric/api/__init__.py
netos_fabric/api/serializers.py
netos_fabric/api/urls.py
netos_fabric/api/views.py
netos_fabric/migrations/0001_initial.py
netos_fabric/migrations/__init__.py
netos_fabric/templates/netos_fabric/networkfabric.html