Metadata-Version: 2.1
Name: netos-fabric
Version: 0.2.0
Summary: An fabric plugin for NetBox
